sewsource/__init__.py
sewsource/main.py
sewsource-0.1.3.dist-info/LICENSE
sewsource-0.1.3.dist-info/METADATA
sewsource-0.1.3.dist-info/WHEEL
sewsource-0.1.3.dist-info/entry_points.txt
sewsource-0.1.3.dist-info/top_level.txt
sewsource-0.1.3.dist-info/RECORD
