Metadata-Version: 2.2
Name: sewsource
Version: 0.1.3
Summary: A CLI tool to sew github documentations into a compiled source for LLMs
Author-email: Keshav Sharma <skeshav0825@gmail.com>
License: MIT License
Project-URL: Homepage, https://github.com/keshavsharma25/sewsource
Project-URL: Repository, https://github.com/keshavsharma25/sewsource
Requires-Python: >=3.8
License-File: LICENSE
Requires-Dist: rich
Requires-Dist: click
Requires-Dist: GitPython
